mps_invidious/__init__.py
mps_invidious/api.py
mps_invidious/cli.py
mps_invidious/util.py
mps_invidious-0.1.2.dist-info/entry_points.txt
mps_invidious-0.1.2.dist-info/WHEEL
mps_invidious-0.1.2.dist-info/METADATA
mps_invidious-0.1.2.dist-info/RECORD
