Metadata-Version: 2.1
Name: mps-invidious
Version: 0.1.2
Summary: 
Author: JoseKilo
Author-email: jose.eduardo.gd@gmail.com
Requires-Python: >=3.10,<4.0
Classifier: Programming Language :: Python :: 3
Classifier: Programming Language :: Python :: 3.10
Requires-Dist: appdirs (>=1.4.4,<2.0.0)
Requires-Dist: requests (>=2.27.1,<3.0.0)
Requires-Dist: rich (>=11.1.0,<12.0.0)
